FIRES/__init__.py
FIRES/main.py
FIRES/functions/__init__.py
FIRES/functions/basicfns.py
FIRES/functions/genfns.py
FIRES/functions/genfrb.py
FIRES/functions/genfrb_parallel.py
FIRES/functions/plotfns.py
FIRES/functions/processfrb.py
FIRES/utils/__init__.py
FIRES/utils/gparams.txt
FIRES/utils/obsparams.txt
FIRES/utils/utils.py
fires-0.4.1.dist-info/licenses/LICENSE
fires-0.4.1.dist-info/METADATA
fires-0.4.1.dist-info/WHEEL
fires-0.4.1.dist-info/entry_points.txt
fires-0.4.1.dist-info/top_level.txt
fires-0.4.1.dist-info/RECORD
