Metadata-Version: 2.4
Name: FIRES
Version: 0.4.1
Summary: A package to simulate Fast Radio Bursts (FRBs) with scattering.
Author-email: Joel Balzan <jbalzan.astro@gmail.com>
License-Expression: MIT
Project-URL: Homepage, https://github.com/JoelBalzan/FIRES
Keywords: FRB,scattering,simulations
Requires-Python: >=3.6
License-File: LICENSE
Dynamic: license-file
